patterns_finder/__init__.py
patterns_finder/finder.py
patterns_finder/version.py
patterns_finder/patterns/__init__.py
patterns_finder/patterns/credit_card.py
patterns_finder/patterns/crypto.py
patterns_finder/patterns/currency.py
patterns_finder/patterns/language.py
patterns_finder/patterns/number.py
patterns_finder/patterns/phone.py
patterns_finder/patterns/postal_code.py
patterns_finder/patterns/time_date.py
patterns_finder/patterns/web.py
patterns_finder-1.0.1.dist-info/LICENSE
patterns_finder-1.0.1.dist-info/METADATA
patterns_finder-1.0.1.dist-info/WHEEL
patterns_finder-1.0.1.dist-info/top_level.txt
patterns_finder-1.0.1.dist-info/RECORD
